datalad_revolution/__init__.py
datalad_revolution/annexrepo.py
datalad_revolution/dataset.py
datalad_revolution/gitrepo.py
datalad_revolution/revcreate.py
datalad_revolution/revdiff.py
datalad_revolution/revsave.py
datalad_revolution/revstatus.py
datalad_revolution/utils.py
datalad_revolution/version.py
datalad_revolution/metadata/__init__.py
datalad_revolution/metadata/query.py
datalad_revolution/metadata/revaggregate.py
datalad_revolution/metadata/revextract.py
datalad_revolution/metadata/extractors/__init__.py
datalad_revolution/metadata/extractors/annex.py
datalad_revolution/metadata/extractors/base.py
datalad_revolution/metadata/extractors/core.py
datalad_revolution/metadata/extractors/custom.py
datalad_revolution/metadata/extractors/tests/__init__.py
datalad_revolution/metadata/extractors/tests/test_annex.py
datalad_revolution/metadata/extractors/tests/test_base.py
datalad_revolution/metadata/extractors/tests/test_custom.py
datalad_revolution/metadata/tests/__init__.py
datalad_revolution/metadata/tests/test_aggregate.py
datalad_revolution/metadata/tests/test_base.py
datalad_revolution/metadata/tests/test_extract.py
datalad_revolution/metadata/tests/test_query.py
datalad_revolution-0.10.0.dist-info/DESCRIPTION.rst
datalad_revolution-0.10.0.dist-info/METADATA
datalad_revolution-0.10.0.dist-info/RECORD
datalad_revolution-0.10.0.dist-info/WHEEL
datalad_revolution-0.10.0.dist-info/entry_points.txt
datalad_revolution-0.10.0.dist-info/metadata.json
datalad_revolution-0.10.0.dist-info/top_level.txt
