Metadata-Version: 2.0
Name: datalad-revolution
Version: 0.10.0
Summary: Revolutionary DataLad extension package
Home-page: UNKNOWN
Author: The DataLad Team and Contributors
Author-email: team@datalad.org
License: UNKNOWN
Platform: UNKNOWN
Requires-Dist: datalad (>=0.12.0rc3)
Requires-Dist: pathlib2; python_version < "3.0"
